{"cameraMode":{"drawMode":0,"name":"Shaded","section":"Shading Mode"},"sceneLighting":true,"audioPlay":false,"sceneViewState":{"m_AlwaysRefresh":false,"showFog":true,"showSkybox":true,"showFlares":true,"showImageEffects":true,"showParticleSystems":true,"showVisualEffectGraphs":true,"m_FxEnabled":true},"in2DMode":false,"pivot":{"x":3.681818962097168,"y":-0.3758692741394043,"z":-37.46123504638672},"rotation":{"x":-0.005285175982862711,"y":-0.9947286248207092,"z":0.07355425506830216,"w":-0.07145336270332337},"size":10.0,"orthographic":false}